citable/__init__.py
citable-0.1.dist-info/LICENSE
citable-0.1.dist-info/METADATA
citable-0.1.dist-info/WHEEL
citable-0.1.dist-info/top_level.txt
citable-0.1.dist-info/RECORD
