Metadata-Version: 2.1
Name: citable
Version: 0.1
Summary: Citable Loader
Home-page: https://github.com/biersabrina/citablePyPI
Author: Gerd Graßhoff, Sabrina Bier, Florian Kotschka
Author-email: gerd.grasshoff@opensciencetechnology.com
License: UNKNOWN
Platform: UNKNOWN
Classifier: Programming Language :: Python :: 3
Classifier: License :: OSI Approved :: MIT License
Classifier: Operating System :: OS Independent
Requires-Python: >=3.6
Requires-Dist: zipfile38
Requires-Dist: requests
Requires-Dist: IPython
Requires-Dist: pandas
Requires-Dist: pyyaml
